jps_git_repo_utils/__init__.py
jps_git_repo_utils/__main__.py
jps_git_repo_utils/audit_repository.py
jps_git_repo_utils/cli.py
jps_git_repo_utils/help.py
jps_git_repo_utils/repo_history.py
jps_git_repo_utils/standardize_branches.py
jps_git_repo_utils-1.0.1.dist-info/licenses/LICENSE
scripts/__init__.py
scripts/audit_repository.py
scripts/help.py
scripts/repo_history.py
scripts/standardize_branches.py
jps_git_repo_utils-1.0.1.dist-info/METADATA
jps_git_repo_utils-1.0.1.dist-info/WHEEL
jps_git_repo_utils-1.0.1.dist-info/entry_points.txt
jps_git_repo_utils-1.0.1.dist-info/top_level.txt
jps_git_repo_utils-1.0.1.dist-info/RECORD
