Metadata-Version: 2.4
Name: jps-git-repo-utils
Version: 1.0.1
Summary: Collection of utility Python scripts to manage code repositories.
Author-email: Jaideep Sundaram <jai.python3@gmail.com>
License: MIT
Project-URL: Homepage, https://github.com/jai-python3/jps-git-repo-utils
Project-URL: Repository, https://github.com/jai-python3/jps-git-repo-utils
Project-URL: Issues, https://github.com/jai-python3/jps-git-repo-utils/issues
Keywords: code-repository,git,gitflow,version-control
Classifier: Programming Language :: Python :: 3
Classifier: License :: OSI Approved :: MIT License
Classifier: Operating System :: OS Independent
Requires-Python: >=3.10
License-File: LICENSE
Requires-Dist: typer>=0.12.3
Requires-Dist: openpyxl~=3.1.5
Provides-Extra: dev
Requires-Dist: flake8<8.0.0,>=7.1.1; extra == "dev"
Requires-Dist: black==24.10.0; extra == "dev"
Requires-Dist: isort==5.13.2; extra == "dev"
Requires-Dist: mypy==1.13.0; extra == "dev"
Requires-Dist: pydocstyle==6.3.0; extra == "dev"
Requires-Dist: darglint==1.8.1; extra == "dev"
Requires-Dist: flake8-docstrings==1.7.0; extra == "dev"
Requires-Dist: bandit==1.7.10; extra == "dev"
Requires-Dist: vulture==2.11; extra == "dev"
Requires-Dist: autoflake==2.3.1; extra == "dev"
Requires-Dist: flynt==1.0.1; extra == "dev"
Requires-Dist: flake8-bugbear==24.8.19; extra == "dev"
Requires-Dist: flake8-comprehensions==3.15.0; extra == "dev"
Requires-Dist: flake8-simplify==0.21.0; extra == "dev"
Requires-Dist: pep8-naming==0.14.0; extra == "dev"
Requires-Dist: pytest==8.3.3; extra == "dev"
Requires-Dist: pytest-cov==5.0.0; extra == "dev"
Requires-Dist: pytest-git==1.8.0; extra == "dev"
Requires-Dist: build==1.2.2.post1; extra == "dev"
Requires-Dist: twine==5.1.1; extra == "dev"
Requires-Dist: pre-commit==4.0.1; extra == "dev"
Requires-Dist: codecov==2.1.13; extra == "dev"
Requires-Dist: pandas==2.2.3; extra == "dev"
Requires-Dist: openpyxl==3.1.5; extra == "dev"
Requires-Dist: bump-my-version>=1.0.1; extra == "dev"
Requires-Dist: git-changelog>=2.7.0; extra == "dev"
Dynamic: license-file
